clickclickclick/__init__.py
clickclickclick-0.0.2.dist-info/METADATA
clickclickclick-0.0.2.dist-info/WHEEL
clickclickclick-0.0.2.dist-info/entry_points.txt
clickclickclick-0.0.2.dist-info/RECORD
